Metadata-Version: 2.1
Name: PyTaskManager72
Version: 1.0.0
Summary: PyTask
Author: dwashere
Author-email: den.langeto45@yandex.ru
Requires-Dist: pyodbc
Requires-Dist: Pillow
